Workbook

Sheet Read me
A1: arq. — Unit Economics Model
A3: What this is | B3: A live unit-economics model for arq. — change any blue cell and every downstream number updates. Use it to stress-test price, physician utilization, CAC, churn, and cohort ramp.
A5: How to use | B5: 1. Go to "Assumptions" — edit any blue cell (yellow cells are the highest-leverage inputs). 2. "Unit Economics" shows per-member monthly P&L at three price tiers. 3. "Sensitivity" shows operating margin across a grid of price × physician-utilization. 4. "Year 1 P&L" models a monthly cohort ramp at ₹15K/member — edit the "New members added" row to flex.
A7: Color key | B7: Blue = editable input · Black = formula · Green = cross-sheet link · Yellow = highest-leverage lever
A9: Headline takeaway | B9: At ₹15K/mo with 100 members/physician, gross margin lands ~69% and operating margin ~35% at steady state. Price below ₹10K and unit economics compress fast because physician cost is a hard floor. Above ₹20K and LTV/CAC exceeds 6x — very healthy.
A11: What is NOT in this model | B11: • Inventory (Rx, supplements) working capital cycle • Setup costs (lab onboarding, app dev amortization) • Tax provisions beyond GST on payment gateway • Founder/exec equity compensation • Cohort retention curves beyond flat monthly churn
A13: Key numbers at ₹15K/100-member steady state | B13: Gross profit per member: ₹10,300/mo Operating profit per member: ₹5,200/mo LTV: ₹343K CAC: ₹12K LTV/CAC: 29x Payback: 1.2 months

Sheet Assumptions
A1: arq. — Unit Economics Model
A2: All inputs on this sheet. Change blue cells to flex the model.
A4: PRICING — MONTHLY PRICE TIERS
A5: Price tier — Low | B5: 10000 | C5: INR/month
A6: Price tier — Mid | B6: 15000 | C6: INR/month
A7: Price tier — High | B7: 20000 | C7: INR/month
A9: DIRECT COGS — PER MEMBER PER MONTH
A10: Bloodwork (quarterly panel amortized) | B10: 1800 | C10: INR/mo
A11: Home phlebotomy (quarterly amortized) | B11: 120 | C11: INR/mo
A12: Kit + Rx logistics (quarterly amortized) | B12: 70 | C12: INR/mo
A13: Software + infra (per member) | B13: 150 | C13: INR/mo
A14: Support, GST overhead (per member) | B14: 150 | C14: INR/mo
A16: PHYSICIAN ECONOMICS
A17: Physician salary (loaded, per month) | B17: 180000 | C17: INR/mo
A18: Members per physician (at scale) | B18: 100 | C18: members
A20: CARE TEAM
A21: Care lead salary (per month) | B21: 40000 | C21: INR/mo
A22: Members per care lead | B22: 150 | C22: members
A24: PAYMENT & TRANSACTION
A25: Payment gateway rate | B25: 0.024 | C25: % of revenue
A27: OPERATING OVERHEAD (% of revenue)
A28: Marketing (blended) | B28: 0.15 | C28: % of revenue
A29: G&A (office, legal, exec) | B29: 0.15 | C29: % of revenue
A31: CUSTOMER ECONOMICS
A32: Blended CAC (acquisition cost) | B32: 12000 | C32: INR per member
A33: Monthly churn rate | B33: 0.03 | C33: % / month
A34: Add-on revenue (blended LTV lift) | B34: 800 | C34: INR/mo per member
A35: Add-on gross margin | B35: 0.4 | C35: %
A36: Prescription margin uplift | B36: 500 | C36: INR/mo per member

Sheet Unit Economics
A1: Per-Member Monthly P&L — Three Price Tiers
A2: All figures INR / member / month. Green = link from Assumptions. Black = formula.
B4: ₹10K tier | C4: ₹15K tier | D4: ₹20K tier
A5: REVENUE
A6: Subscription price | B6: =Assumptions!B5 -> 10000 | C6: =Assumptions!B6 -> 15000 | D6: =Assumptions!B7 -> 20000
A7: Add-on revenue (blended) | B7: =Assumptions!B34 -> 800 | C7: =Assumptions!B34 -> 800 | D7: =Assumptions!B34 -> 800
A8: Gross revenue | B8: =SUM(B6:B7) -> 10800 | C8: =SUM(C6:C7) -> 15800 | D8: =SUM(D6:D7) -> 20800
A9: Payment gateway fee | B9: =-B8*Assumptions!B25 -> -259.2 | C9: =-C8*Assumptions!B25 -> -379.2 | D9: =-D8*Assumptions!B25 -> -499.2
A10: Net revenue | B10: =B8+B9 -> 10540.8 | C10: =C8+C9 -> 15420.8 | D10: =D8+D9 -> 20300.8
A12: DIRECT COGS
A13: Bloodwork | B13: =-Assumptions!B10 -> -1800 | C13: =-Assumptions!B10 -> -1800 | D13: =-Assumptions!B10 -> -1800
A14: Home phlebotomy | B14: =-Assumptions!B11 -> -120 | C14: =-Assumptions!B11 -> -120 | D14: =-Assumptions!B11 -> -120
A15: Kit + Rx logistics | B15: =-Assumptions!B12 -> -70 | C15: =-Assumptions!B12 -> -70 | D15: =-Assumptions!B12 -> -70
A16: Physician (loaded, per member) | B16: =-Assumptions!B17/Assumptions!B18 -> -1800 | C16: =-Assumptions!B17/Assumptions!B18 -> -1800 | D16: =-Assumptions!B17/Assumptions!B18 -> -1800
A17: Care lead | B17: =-Assumptions!B21/Assumptions!B22 -> -266.66667 | C17: =-Assumptions!B21/Assumptions!B22 -> -266.66667 | D17: =-Assumptions!B21/Assumptions!B22 -> -266.66667
A18: Software + infra | B18: =-Assumptions!B13 -> -150 | C18: =-Assumptions!B13 -> -150 | D18: =-Assumptions!B13 -> -150
A19: Support + overhead | B19: =-Assumptions!B14 -> -150 | C19: =-Assumptions!B14 -> -150 | D19: =-Assumptions!B14 -> -150
A20: Add-on COGS | B20: =-Assumptions!B34*(1-Assumptions!B35) -> -480 | C20: =-Assumptions!B34*(1-Assumptions!B35) -> -480 | D20: =-Assumptions!B34*(1-Assumptions!B35) -> -480
A21: Total COGS | B21: =SUM(B13:B20) -> -4836.6667 | C21: =SUM(C13:C20) -> -4836.6667 | D21: =SUM(D13:D20) -> -4836.6667
A22: Rx margin uplift | B22: =Assumptions!B36 -> 500 | C22: =Assumptions!B36 -> 500 | D22: =Assumptions!B36 -> 500
A23: Gross profit | B23: =B10+B21+B22 -> 6204.1333 | C23: =C10+C21+C22 -> 11084.133 | D23: =D10+D21+D22 -> 15964.133
A24: Gross margin % | B24: =B23/B8 -> 0.57445679 | C24: =C23/C8 -> 0.70152743 | D24: =D23/D8 -> 0.76750641
A26: OPERATING EXPENSES
A27: Marketing | B27: =-B8*Assumptions!B28 -> -1620 | C27: =-C8*Assumptions!B28 -> -2370 | D27: =-D8*Assumptions!B28 -> -3120
A28: G&A | B28: =-B8*Assumptions!B29 -> -1620 | C28: =-C8*Assumptions!B29 -> -2370 | D28: =-D8*Assumptions!B29 -> -3120
A29: Total OpEx | B29: =SUM(B27:B28) -> -3240 | C29: =SUM(C27:C28) -> -4740 | D29: =SUM(D27:D28) -> -6240
A30: Operating profit | B30: =B23+B29 -> 2964.1333 | C30: =C23+C29 -> 6344.1333 | D30: =D23+D29 -> 9724.1333
A31: Operating margin % | B31: =B30/B8 -> 0.27445679 | C31: =C30/C8 -> 0.40152743 | D31: =D30/D8 -> 0.46750641
A33: KEY RATIOS
A34: LTV (1/churn × gross profit) | B34: =B23/Assumptions!B33 -> 206804.44 | C34: =C23/Assumptions!B33 -> 369471.11 | D34: =D23/Assumptions!B33 -> 532137.78
A35: CAC | B35: =Assumptions!B32 -> 12000 | C35: =Assumptions!B32 -> 12000 | D35: =Assumptions!B32 -> 12000
A36: LTV / CAC multiple | B36: =B34/B35 -> 17.233704 | C36: =C34/C35 -> 30.789259 | D36: =D34/D35 -> 44.344815
A37: CAC payback (months) | B37: =B35/B23 -> 1.9341944 | C37: =C35/C23 -> 1.0826286 | D37: =D35/D23 -> 0.75168503
A38: Avg member lifetime (months) | B38: =1/Assumptions!B33 -> 33.333333 | C38: =1/Assumptions!B33 -> 33.333333 | D38: =1/Assumptions!B33 -> 33.333333

Sheet Sensitivity
A1: Operating Margin % — Price × Physician Utilization
A2: Rows = members per physician. Cols = monthly price tier. Cells = operating margin %.
A4: Members / physician → ↓ Monthly price | B4: 30 | C4: 50 | D4: 70 | E4: 90 | F4: 100 | G4: 120 | H4: 150
A5: 8000 | B5: =((($A5+Assumptions!B34)*(1-Assumptions!B25))-(Assumptions!B10+Assumptions!B11+Assumptions!B12+Assumptions!B17/B$4+Assumptions!B21/Assumptions!B22+Assumptions!B13+Assumptions!B14+Assumptions!B34*(1-Assumptions!B35))+Assumptions!B36-(($A5+Assumptions!B34)*(Assumptions!B28+Assumptions!B29)))/($A5+Assumptions!B34) -> -0.29407576 | C5: =((($A5+Assumptions!B34)*(1-Assumptions!B25))-(Assumptions!B10+Assumptions!B11+Assumptions!B12+Assumptions!B17/C$4+Assumptions!B21/Assumptions!B22+Assumptions!B13+Assumptions!B14+Assumptions!B34*(1-Assumptions!B35))+Assumptions!B36-(($A5+Assumptions!B34)*(Assumptions!B28+Assumptions!B29)))/($A5+Assumptions!B34) -> -0.021348485 | D5: =((($A5+Assumptions!B34)*(1-Assumptions!B25))-(Assumptions!B10+Assumptions!B11+Assumptions!B12+Assumptions!B17/D$4+Assumptions!B21/Assumptions!B22+Assumptions!B13+Assumptions!B14+Assumptions!B34*(1-Assumptions!B35))+Assumptions!B36-(($A5+Assumptions!B34)*(Assumptions!B28+Assumptions!B29)))/($A5+Assumptions!B34) -> 0.095534632 | E5: =((($A5+Assumptions!B34)*(1-Assumptions!B25))-(Assumptions!B10+Assumptions!B11+Assumptions!B12+Assumptions!B17/E$4+Assumptions!B21/Assumptions!B22+Assumptions!B13+Assumptions!B14+Assumptions!B34*(1-Assumptions!B35))+Assumptions!B36-(($A5+Assumptions!B34)*(Assumptions!B28+Assumptions!B29)))/($A5+Assumptions!B34) -> 0.1604697 | F5: =((($A5+Assumptions!B34)*(1-Assumptions!B25))-(Assumptions!B10+Assumptions!B11+Assumptions!B12+Assumptions!B17/F$4+Assumptions!B21/Assumptions!B22+Assumptions!B13+Assumptions!B14+Assumptions!B34*(1-Assumptions!B35))+Assumptions!B36-(($A5+Assumptions!B34)*(Assumptions!B28+Assumptions!B29)))/($A5+Assumptions!B34) -> 0.18319697 | G5: =((($A5+Assumptions!B34)*(1-Assumptions!B25))-(Assumptions!B10+Assumptions!B11+Assumptions!B12+Assumptions!B17/G$4+Assumptions!B21/Assumptions!B22+Assumptions!B13+Assumptions!B14+Assumptions!B34*(1-Assumptions!B35))+Assumptions!B36-(($A5+Assumptions!B34)*(Assumptions!B28+Assumptions!B29)))/($A5+Assumptions!B34) -> 0.21728788 | H5: =((($A5+Assumptions!B34)*(1-Assumptions!B25))-(Assumptions!B10+Assumptions!B11+Assumptions!B12+Assumptions!B17/H$4+Assumptions!B21/Assumptions!B22+Assumptions!B13+Assumptions!B14+Assumptions!B34*(1-Assumptions!B35))+Assumptions!B36-(($A5+Assumptions!B34)*(Assumptions!B28+Assumptions!B29)))/($A5+Assumptions!B34) -> 0.25137879
A6: 10000 | B6: =((($A6+Assumptions!B34)*(1-Assumptions!B25))-(Assumptions!B10+Assumptions!B11+Assumptions!B12+Assumptions!B17/B$4+Assumptions!B21/Assumptions!B22+Assumptions!B13+Assumptions!B14+Assumptions!B34*(1-Assumptions!B35))+Assumptions!B36-(($A6+Assumptions!B34)*(Assumptions!B28+Assumptions!B29)))/($A6+Assumptions!B34) -> -0.1144321 | C6: =((($A6+Assumptions!B34)*(1-Assumptions!B25))-(Assumptions!B10+Assumptions!B11+Assumptions!B12+Assumptions!B17/C$4+Assumptions!B21/Assumptions!B22+Assumptions!B13+Assumptions!B14+Assumptions!B34*(1-Assumptions!B35))+Assumptions!B36-(($A6+Assumptions!B34)*(Assumptions!B28+Assumptions!B29)))/($A6+Assumptions!B34) -> 0.10779012 | D6: =((($A6+Assumptions!B34)*(1-Assumptions!B25))-(Assumptions!B10+Assumptions!B11+Assumptions!B12+Assumptions!B17/D$4+Assumptions!B21/Assumptions!B22+Assumptions!B13+Assumptions!B14+Assumptions!B34*(1-Assumptions!B35))+Assumptions!B36-(($A6+Assumptions!B34)*(Assumptions!B28+Assumptions!B29)))/($A6+Assumptions!B34) -> 0.20302822 | E6: =((($A6+Assumptions!B34)*(1-Assumptions!B25))-(Assumptions!B10+Assumptions!B11+Assumptions!B12+Assumptions!B17/E$4+Assumptions!B21/Assumptions!B22+Assumptions!B13+Assumptions!B14+Assumptions!B34*(1-Assumptions!B35))+Assumptions!B36-(($A6+Assumptions!B34)*(Assumptions!B28+Assumptions!B29)))/($A6+Assumptions!B34) -> 0.25593827 | F6: =((($A6+Assumptions!B34)*(1-Assumptions!B25))-(Assumptions!B10+Assumptions!B11+Assumptions!B12+Assumptions!B17/F$4+Assumptions!B21/Assumptions!B22+Assumptions!B13+Assumptions!B14+Assumptions!B34*(1-Assumptions!B35))+Assumptions!B36-(($A6+Assumptions!B34)*(Assumptions!B28+Assumptions!B29)))/($A6+Assumptions!B34) -> 0.27445679 | G6: =((($A6+Assumptions!B34)*(1-Assumptions!B25))-(Assumptions!B10+Assumptions!B11+Assumptions!B12+Assumptions!B17/G$4+Assumptions!B21/Assumptions!B22+Assumptions!B13+Assumptions!B14+Assumptions!B34*(1-Assumptions!B35))+Assumptions!B36-(($A6+Assumptions!B34)*(Assumptions!B28+Assumptions!B29)))/($A6+Assumptions!B34) -> 0.30223457 | H6: =((($A6+Assumptions!B34)*(1-Assumptions!B25))-(Assumptions!B10+Assumptions!B11+Assumptions!B12+Assumptions!B17/H$4+Assumptions!B21/Assumptions!B22+Assumptions!B13+Assumptions!B14+Assumptions!B34*(1-Assumptions!B35))+Assumptions!B36-(($A6+Assumptions!B34)*(Assumptions!B28+Assumptions!B29)))/($A6+Assumptions!B34) -> 0.33001235
A7: 12000 | B7: =((($A7+Assumptions!B34)*(1-Assumptions!B25))-(Assumptions!B10+Assumptions!B11+Assumptions!B12+Assumptions!B17/B$4+Assumptions!B21/Assumptions!B22+Assumptions!B13+Assumptions!B14+Assumptions!B34*(1-Assumptions!B35))+Assumptions!B36-(($A7+Assumptions!B34)*(Assumptions!B28+Assumptions!B29)))/($A7+Assumptions!B34) -> 0.0090729167 | C7: =((($A7+Assumptions!B34)*(1-Assumptions!B25))-(Assumptions!B10+Assumptions!B11+Assumptions!B12+Assumptions!B17/C$4+Assumptions!B21/Assumptions!B22+Assumptions!B13+Assumptions!B14+Assumptions!B34*(1-Assumptions!B35))+Assumptions!B36-(($A7+Assumptions!B34)*(Assumptions!B28+Assumptions!B29)))/($A7+Assumptions!B34) -> 0.19657292 | D7: =((($A7+Assumptions!B34)*(1-Assumptions!B25))-(Assumptions!B10+Assumptions!B11+Assumptions!B12+Assumptions!B17/D$4+Assumptions!B21/Assumptions!B22+Assumptions!B13+Assumptions!B14+Assumptions!B34*(1-Assumptions!B35))+Assumptions!B36-(($A7+Assumptions!B34)*(Assumptions!B28+Assumptions!B29)))/($A7+Assumptions!B34) -> 0.27693006 | E7: =((($A7+Assumptions!B34)*(1-Assumptions!B25))-(Assumptions!B10+Assumptions!B11+Assumptions!B12+Assumptions!B17/E$4+Assumptions!B21/Assumptions!B22+Assumptions!B13+Assumptions!B14+Assumptions!B34*(1-Assumptions!B35))+Assumptions!B36-(($A7+Assumptions!B34)*(Assumptions!B28+Assumptions!B29)))/($A7+Assumptions!B34) -> 0.32157292 | F7: =((($A7+Assumptions!B34)*(1-Assumptions!B25))-(Assumptions!B10+Assumptions!B11+Assumptions!B12+Assumptions!B17/F$4+Assumptions!B21/Assumptions!B22+Assumptions!B13+Assumptions!B14+Assumptions!B34*(1-Assumptions!B35))+Assumptions!B36-(($A7+Assumptions!B34)*(Assumptions!B28+Assumptions!B29)))/($A7+Assumptions!B34) -> 0.33719792 | G7: =((($A7+Assumptions!B34)*(1-Assumptions!B25))-(Assumptions!B10+Assumptions!B11+Assumptions!B12+Assumptions!B17/G$4+Assumptions!B21/Assumptions!B22+Assumptions!B13+Assumptions!B14+Assumptions!B34*(1-Assumptions!B35))+Assumptions!B36-(($A7+Assumptions!B34)*(Assumptions!B28+Assumptions!B29)))/($A7+Assumptions!B34) -> 0.36063542 | H7: =((($A7+Assumptions!B34)*(1-Assumptions!B25))-(Assumptions!B10+Assumptions!B11+Assumptions!B12+Assumptions!B17/H$4+Assumptions!B21/Assumptions!B22+Assumptions!B13+Assumptions!B14+Assumptions!B34*(1-Assumptions!B35))+Assumptions!B36-(($A7+Assumptions!B34)*(Assumptions!B28+Assumptions!B29)))/($A7+Assumptions!B34) -> 0.38407292
A8: 15000 | B8: =((($A8+Assumptions!B34)*(1-Assumptions!B25))-(Assumptions!B10+Assumptions!B11+Assumptions!B12+Assumptions!B17/B$4+Assumptions!B21/Assumptions!B22+Assumptions!B13+Assumptions!B14+Assumptions!B34*(1-Assumptions!B35))+Assumptions!B36-(($A8+Assumptions!B34)*(Assumptions!B28+Assumptions!B29)))/($A8+Assumptions!B34) -> 0.13570464 | C8: =((($A8+Assumptions!B34)*(1-Assumptions!B25))-(Assumptions!B10+Assumptions!B11+Assumptions!B12+Assumptions!B17/C$4+Assumptions!B21/Assumptions!B22+Assumptions!B13+Assumptions!B14+Assumptions!B34*(1-Assumptions!B35))+Assumptions!B36-(($A8+Assumptions!B34)*(Assumptions!B28+Assumptions!B29)))/($A8+Assumptions!B34) -> 0.28760338 | D8: =((($A8+Assumptions!B34)*(1-Assumptions!B25))-(Assumptions!B10+Assumptions!B11+Assumptions!B12+Assumptions!B17/D$4+Assumptions!B21/Assumptions!B22+Assumptions!B13+Assumptions!B14+Assumptions!B34*(1-Assumptions!B35))+Assumptions!B36-(($A8+Assumptions!B34)*(Assumptions!B28+Assumptions!B29)))/($A8+Assumptions!B34) -> 0.35270283 | E8: =((($A8+Assumptions!B34)*(1-Assumptions!B25))-(Assumptions!B10+Assumptions!B11+Assumptions!B12+Assumptions!B17/E$4+Assumptions!B21/Assumptions!B22+Assumptions!B13+Assumptions!B14+Assumptions!B34*(1-Assumptions!B35))+Assumptions!B36-(($A8+Assumptions!B34)*(Assumptions!B28+Assumptions!B29)))/($A8+Assumptions!B34) -> 0.3888692 | F8: =((($A8+Assumptions!B34)*(1-Assumptions!B25))-(Assumptions!B10+Assumptions!B11+Assumptions!B12+Assumptions!B17/F$4+Assumptions!B21/Assumptions!B22+Assumptions!B13+Assumptions!B14+Assumptions!B34*(1-Assumptions!B35))+Assumptions!B36-(($A8+Assumptions!B34)*(Assumptions!B28+Assumptions!B29)))/($A8+Assumptions!B34) -> 0.40152743 | G8: =((($A8+Assumptions!B34)*(1-Assumptions!B25))-(Assumptions!B10+Assumptions!B11+Assumptions!B12+Assumptions!B17/G$4+Assumptions!B21/Assumptions!B22+Assumptions!B13+Assumptions!B14+Assumptions!B34*(1-Assumptions!B35))+Assumptions!B36-(($A8+Assumptions!B34)*(Assumptions!B28+Assumptions!B29)))/($A8+Assumptions!B34) -> 0.42051477 | H8: =((($A8+Assumptions!B34)*(1-Assumptions!B25))-(Assumptions!B10+Assumptions!B11+Assumptions!B12+Assumptions!B17/H$4+Assumptions!B21/Assumptions!B22+Assumptions!B13+Assumptions!B14+Assumptions!B34*(1-Assumptions!B35))+Assumptions!B36-(($A8+Assumptions!B34)*(Assumptions!B28+Assumptions!B29)))/($A8+Assumptions!B34) -> 0.43950211
A9: 18000 | B9: =((($A9+Assumptions!B34)*(1-Assumptions!B25))-(Assumptions!B10+Assumptions!B11+Assumptions!B12+Assumptions!B17/B$4+Assumptions!B21/Assumptions!B22+Assumptions!B13+Assumptions!B14+Assumptions!B34*(1-Assumptions!B35))+Assumptions!B36-(($A9+Assumptions!B34)*(Assumptions!B28+Assumptions!B29)))/($A9+Assumptions!B34) -> 0.22192199 | C9: =((($A9+Assumptions!B34)*(1-Assumptions!B25))-(Assumptions!B10+Assumptions!B11+Assumptions!B12+Assumptions!B17/C$4+Assumptions!B21/Assumptions!B22+Assumptions!B13+Assumptions!B14+Assumptions!B34*(1-Assumptions!B35))+Assumptions!B36-(($A9+Assumptions!B34)*(Assumptions!B28+Assumptions!B29)))/($A9+Assumptions!B34) -> 0.34958156 | D9: =((($A9+Assumptions!B34)*(1-Assumptions!B25))-(Assumptions!B10+Assumptions!B11+Assumptions!B12+Assumptions!B17/D$4+Assumptions!B21/Assumptions!B22+Assumptions!B13+Assumptions!B14+Assumptions!B34*(1-Assumptions!B35))+Assumptions!B36-(($A9+Assumptions!B34)*(Assumptions!B28+Assumptions!B29)))/($A9+Assumptions!B34) -> 0.40429281 | E9: =((($A9+Assumptions!B34)*(1-Assumptions!B25))-(Assumptions!B10+Assumptions!B11+Assumptions!B12+Assumptions!B17/E$4+Assumptions!B21/Assumptions!B22+Assumptions!B13+Assumptions!B14+Assumptions!B34*(1-Assumptions!B35))+Assumptions!B36-(($A9+Assumptions!B34)*(Assumptions!B28+Assumptions!B29)))/($A9+Assumptions!B34) -> 0.43468794 | F9: =((($A9+Assumptions!B34)*(1-Assumptions!B25))-(Assumptions!B10+Assumptions!B11+Assumptions!B12+Assumptions!B17/F$4+Assumptions!B21/Assumptions!B22+Assumptions!B13+Assumptions!B14+Assumptions!B34*(1-Assumptions!B35))+Assumptions!B36-(($A9+Assumptions!B34)*(Assumptions!B28+Assumptions!B29)))/($A9+Assumptions!B34) -> 0.44532624 | G9: =((($A9+Assumptions!B34)*(1-Assumptions!B25))-(Assumptions!B10+Assumptions!B11+Assumptions!B12+Assumptions!B17/G$4+Assumptions!B21/Assumptions!B22+Assumptions!B13+Assumptions!B14+Assumptions!B34*(1-Assumptions!B35))+Assumptions!B36-(($A9+Assumptions!B34)*(Assumptions!B28+Assumptions!B29)))/($A9+Assumptions!B34) -> 0.46128369 | H9: =((($A9+Assumptions!B34)*(1-Assumptions!B25))-(Assumptions!B10+Assumptions!B11+Assumptions!B12+Assumptions!B17/H$4+Assumptions!B21/Assumptions!B22+Assumptions!B13+Assumptions!B14+Assumptions!B34*(1-Assumptions!B35))+Assumptions!B36-(($A9+Assumptions!B34)*(Assumptions!B28+Assumptions!B29)))/($A9+Assumptions!B34) -> 0.47724113
A10: 20000 | B10: =((($A10+Assumptions!B34)*(1-Assumptions!B25))-(Assumptions!B10+Assumptions!B11+Assumptions!B12+Assumptions!B17/B$4+Assumptions!B21/Assumptions!B22+Assumptions!B13+Assumptions!B14+Assumptions!B34*(1-Assumptions!B35))+Assumptions!B36-(($A10+Assumptions!B34)*(Assumptions!B28+Assumptions!B29)))/($A10+Assumptions!B34) -> 0.26558333 | C10: =((($A10+Assumptions!B34)*(1-Assumptions!B25))-(Assumptions!B10+Assumptions!B11+Assumptions!B12+Assumptions!B17/C$4+Assumptions!B21/Assumptions!B22+Assumptions!B13+Assumptions!B14+Assumptions!B34*(1-Assumptions!B35))+Assumptions!B36-(($A10+Assumptions!B34)*(Assumptions!B28+Assumptions!B29)))/($A10+Assumptions!B34) -> 0.38096795 | D10: =((($A10+Assumptions!B34)*(1-Assumptions!B25))-(Assumptions!B10+Assumptions!B11+Assumptions!B12+Assumptions!B17/D$4+Assumptions!B21/Assumptions!B22+Assumptions!B13+Assumptions!B14+Assumptions!B34*(1-Assumptions!B35))+Assumptions!B36-(($A10+Assumptions!B34)*(Assumptions!B28+Assumptions!B29)))/($A10+Assumptions!B34) -> 0.4304185 | E10: =((($A10+Assumptions!B34)*(1-Assumptions!B25))-(Assumptions!B10+Assumptions!B11+Assumptions!B12+Assumptions!B17/E$4+Assumptions!B21/Assumptions!B22+Assumptions!B13+Assumptions!B14+Assumptions!B34*(1-Assumptions!B35))+Assumptions!B36-(($A10+Assumptions!B34)*(Assumptions!B28+Assumptions!B29)))/($A10+Assumptions!B34) -> 0.45789103 | F10: =((($A10+Assumptions!B34)*(1-Assumptions!B25))-(Assumptions!B10+Assumptions!B11+Assumptions!B12+Assumptions!B17/F$4+Assumptions!B21/Assumptions!B22+Assumptions!B13+Assumptions!B14+Assumptions!B34*(1-Assumptions!B35))+Assumptions!B36-(($A10+Assumptions!B34)*(Assumptions!B28+Assumptions!B29)))/($A10+Assumptions!B34) -> 0.46750641 | G10: =((($A10+Assumptions!B34)*(1-Assumptions!B25))-(Assumptions!B10+Assumptions!B11+Assumptions!B12+Assumptions!B17/G$4+Assumptions!B21/Assumptions!B22+Assumptions!B13+Assumptions!B14+Assumptions!B34*(1-Assumptions!B35))+Assumptions!B36-(($A10+Assumptions!B34)*(Assumptions!B28+Assumptions!B29)))/($A10+Assumptions!B34) -> 0.48192949 | H10: =((($A10+Assumptions!B34)*(1-Assumptions!B25))-(Assumptions!B10+Assumptions!B11+Assumptions!B12+Assumptions!B17/H$4+Assumptions!B21/Assumptions!B22+Assumptions!B13+Assumptions!B14+Assumptions!B34*(1-Assumptions!B35))+Assumptions!B36-(($A10+Assumptions!B34)*(Assumptions!B28+Assumptions!B29)))/($A10+Assumptions!B34) -> 0.49635256
A11: 25000 | B11: =((($A11+Assumptions!B34)*(1-Assumptions!B25))-(Assumptions!B10+Assumptions!B11+Assumptions!B12+Assumptions!B17/B$4+Assumptions!B21/Assumptions!B22+Assumptions!B13+Assumptions!B14+Assumptions!B34*(1-Assumptions!B35))+Assumptions!B36-(($A11+Assumptions!B34)*(Assumptions!B28+Assumptions!B29)))/($A11+Assumptions!B34) -> 0.34512145 | C11: =((($A11+Assumptions!B34)*(1-Assumptions!B25))-(Assumptions!B10+Assumptions!B11+Assumptions!B12+Assumptions!B17/C$4+Assumptions!B21/Assumptions!B22+Assumptions!B13+Assumptions!B14+Assumptions!B34*(1-Assumptions!B35))+Assumptions!B36-(($A11+Assumptions!B34)*(Assumptions!B28+Assumptions!B29)))/($A11+Assumptions!B34) -> 0.4381447 | D11: =((($A11+Assumptions!B34)*(1-Assumptions!B25))-(Assumptions!B10+Assumptions!B11+Assumptions!B12+Assumptions!B17/D$4+Assumptions!B21/Assumptions!B22+Assumptions!B13+Assumptions!B14+Assumptions!B34*(1-Assumptions!B35))+Assumptions!B36-(($A11+Assumptions!B34)*(Assumptions!B28+Assumptions!B29)))/($A11+Assumptions!B34) -> 0.47801181 | E11: =((($A11+Assumptions!B34)*(1-Assumptions!B25))-(Assumptions!B10+Assumptions!B11+Assumptions!B12+Assumptions!B17/E$4+Assumptions!B21/Assumptions!B22+Assumptions!B13+Assumptions!B14+Assumptions!B34*(1-Assumptions!B35))+Assumptions!B36-(($A11+Assumptions!B34)*(Assumptions!B28+Assumptions!B29)))/($A11+Assumptions!B34) -> 0.50016021 | F11: =((($A11+Assumptions!B34)*(1-Assumptions!B25))-(Assumptions!B10+Assumptions!B11+Assumptions!B12+Assumptions!B17/F$4+Assumptions!B21/Assumptions!B22+Assumptions!B13+Assumptions!B14+Assumptions!B34*(1-Assumptions!B35))+Assumptions!B36-(($A11+Assumptions!B34)*(Assumptions!B28+Assumptions!B29)))/($A11+Assumptions!B34) -> 0.50791214 | G11: =((($A11+Assumptions!B34)*(1-Assumptions!B25))-(Assumptions!B10+Assumptions!B11+Assumptions!B12+Assumptions!B17/G$4+Assumptions!B21/Assumptions!B22+Assumptions!B13+Assumptions!B14+Assumptions!B34*(1-Assumptions!B35))+Assumptions!B36-(($A11+Assumptions!B34)*(Assumptions!B28+Assumptions!B29)))/($A11+Assumptions!B34) -> 0.51954005 | H11: =((($A11+Assumptions!B34)*(1-Assumptions!B25))-(Assumptions!B10+Assumptions!B11+Assumptions!B12+Assumptions!B17/H$4+Assumptions!B21/Assumptions!B22+Assumptions!B13+Assumptions!B14+Assumptions!B34*(1-Assumptions!B35))+Assumptions!B36-(($A11+Assumptions!B34)*(Assumptions!B28+Assumptions!B29)))/($A11+Assumptions!B34) -> 0.53116796
A14: Reading this table:
A15: • Green zone: >35% operating margin — scalable
A16: • Red zone: <10% operating margin — unit economics broken
A17: • Gold cell: current plan (₹15K/mo, 100 members/physician)

Sheet Year 1 P&L
A1: Year 1 Monthly P&L — @ ₹15K tier
A2: Member ramp with physician utilization growing as members grow. Change cohort adds (blue) to flex.
B4: M1 | C4: M2 | D4: M3 | E4: M4 | F4: M5 | G4: M6 | H4: M7 | I4: M8 | J4: M9 | K4: M10 | L4: M11 | M4: M12 | N4: Total
A5: New members added | B5: 10 | C5: 15 | D5: 25 | E5: 35 | F5: 50 | G5: 60 | H5: 70 | I5: 80 | J5: 90 | K5: 95 | L5: 100 | M5: 100 | N5: =SUM(B5:M5) -> 730
A6: Monthly churn % | B6: =Assumptions!B33 -> 0.03 | C6: =Assumptions!B33 -> 0.03 | D6: =Assumptions!B33 -> 0.03 | E6: =Assumptions!B33 -> 0.03 | F6: =Assumptions!B33 -> 0.03 | G6: =Assumptions!B33 -> 0.03 | H6: =Assumptions!B33 -> 0.03 | I6: =Assumptions!B33 -> 0.03 | J6: =Assumptions!B33 -> 0.03 | K6: =Assumptions!B33 -> 0.03 | L6: =Assumptions!B33 -> 0.03 | M6: =Assumptions!B33 -> 0.03
A7: Active members (EoM) | B7: =B5 -> 10 | C7: =B7*(1-C6)+C5 -> 24.7 | D7: =C7*(1-D6)+D5 -> 48.959 | E7: =D7*(1-E6)+E5 -> 82.49023 | F7: =E7*(1-F6)+F5 -> 130.01552 | G7: =F7*(1-G6)+G5 -> 186.11506 | H7: =G7*(1-H6)+H5 -> 250.53161 | I7: =H7*(1-I6)+I5 -> 323.01566 | J7: =I7*(1-J6)+J5 -> 403.32519 | ... M7: =L7*(1-M6)+M5 -> 654.48951
A8: Avg active members | B8: =B7/2 -> 5 | C8: =(B7+C7)/2 -> 17.35 | D8: =(C7+D7)/2 -> 36.8295 | E8: =(D7+E7)/2 -> 65.724615 | F8: =(E7+F7)/2 -> 106.25288 | G8: =(F7+G7)/2 -> 158.06529 | H8: =(G7+H7)/2 -> 218.32333 | I8: =(H7+I7)/2 -> 286.77363 | J8: =(I7+J7)/2 -> 363.17042 | ... M8: =(L7+M7)/2 -> 613.06409
A10: REVENUE
A11: Subscription revenue | B11: =B8*Assumptions!B6 -> 75000 | C11: =C8*Assumptions!B6 -> 260250 | D11: =D8*Assumptions!B6 -> 552442.5 | E11: =E8*Assumptions!B6 -> 985869.22 | F11: =F8*Assumptions!B6 -> 1593793.1 | G11: =G8*Assumptions!B6 -> 2370979.4 | H11: =H8*Assumptions!B6 -> 3274850 | I11: =I8*Assumptions!B6 -> 4301604.5 | J11: =J8*Assumptions!B6 -> 5447556.3 | K11: =K8*Assumptions!B6 -> 6671629.6 | L11: =L8*Assumptions!B6 -> 7933980.8 | M11: =M8*Assumptions!B6 -> 9195961.3 | N11: =SUM(B11:M11) -> 42663917
A12: Add-on revenue | B12: =B8*Assumptions!B34 -> 4000 | C12: =C8*Assumptions!B34 -> 13880 | D12: =D8*Assumptions!B34 -> 29463.6 | E12: =E8*Assumptions!B34 -> 52579.692 | F12: =F8*Assumptions!B34 -> 85002.301 | G12: =G8*Assumptions!B34 -> 126452.23 | H12: =H8*Assumptions!B34 -> 174658.67 | I12: =I8*Assumptions!B34 -> 229418.91 | J12: =J8*Assumptions!B34 -> 290536.34 | K12: =K8*Assumptions!B34 -> 355820.25 | L12: =L8*Assumptions!B34 -> 423145.64 | M12: =M8*Assumptions!B34 -> 490451.27 | N12: =SUM(B12:M12) -> 2275408.9
A13: Gross revenue | B13: =B11+B12 -> 79000 | C13: =C11+C12 -> 274130 | D13: =D11+D12 -> 581906.1 | E13: =E11+E12 -> 1038448.9 | F13: =F11+F12 -> 1678795.4 | G13: =G11+G12 -> 2497431.6 | H13: =H11+H12 -> 3449508.6 | I13: =I11+I12 -> 4531023.4 | ... M13: =M11+M12 -> 9686412.6 | N13: =SUM(B13:M13) -> 44939326
A14: Payment gateway | B14: =-B13*Assumptions!B25 -> -1896 | C14: =-C13*Assumptions!B25 -> -6579.12 | D14: =-D13*Assumptions!B25 -> -13965.746 | E14: =-E13*Assumptions!B25 -> -24922.774 | F14: =-F13*Assumptions!B25 -> -40291.091 | G14: =-G13*Assumptions!B25 -> -59938.358 | H14: =-H13*Assumptions!B25 -> -82788.207 | I14: =-I13*Assumptions!B25 -> -108744.56 | J14: =-J13*Assumptions!B25 -> -137714.22 | K14: =-K13*Assumptions!B25 -> -168658.8 | L14: =-L13*Assumptions!B25 -> -200571.03 | M14: =-M13*Assumptions!B25 -> -232473.9 | N14: =SUM(B14:M14) -> -1078543.8
A15: Net revenue | B15: =B13+B14 -> 77104 | C15: =C13+C14 -> 267550.88 | D15: =D13+D14 -> 567940.35 | E15: =E13+E14 -> 1013526.1 | F15: =F13+F14 -> 1638504.4 | G15: =G13+G14 -> 2437493.2 | H15: =H13+H14 -> 3366720.4 | I15: =I13+I14 -> 4422278.8 | ... M15: =M13+M14 -> 9453938.7 | N15: =SUM(B15:M15) -> 43860782
A17: COGS (VARIABLE)
A18: Bloodwork | B18: =-B8*Assumptions!B10 -> -9000 | C18: =-C8*Assumptions!B10 -> -31230 | D18: =-D8*Assumptions!B10 -> -66293.1 | E18: =-E8*Assumptions!B10 -> -118304.31 | F18: =-F8*Assumptions!B10 -> -191255.18 | G18: =-G8*Assumptions!B10 -> -284517.52 | H18: =-H8*Assumptions!B10 -> -392982 | I18: =-I8*Assumptions!B10 -> -516192.54 | J18: =-J8*Assumptions!B10 -> -653706.76 | K18: =-K8*Assumptions!B10 -> -800595.56 | L18: =-L8*Assumptions!B10 -> -952077.69 | M18: =-M8*Assumptions!B10 -> -1103515.4 | N18: =SUM(B18:M18) -> -5119670
A19: Phlebotomy | B19: =-B8*Assumptions!B11 -> -600 | C19: =-C8*Assumptions!B11 -> -2082 | D19: =-D8*Assumptions!B11 -> -4419.54 | E19: =-E8*Assumptions!B11 -> -7886.9538 | F19: =-F8*Assumptions!B11 -> -12750.345 | G19: =-G8*Assumptions!B11 -> -18967.835 | H19: =-H8*Assumptions!B11 -> -26198.8 | I19: =-I8*Assumptions!B11 -> -34412.836 | J19: =-J8*Assumptions!B11 -> -43580.451 | K19: =-K8*Assumptions!B11 -> -53373.037 | L19: =-L8*Assumptions!B11 -> -63471.846 | M19: =-M8*Assumptions!B11 -> -73567.691 | N19: =SUM(B19:M19) -> -341311.33
A20: Logistics | B20: =-B8*Assumptions!B12 -> -350 | C20: =-C8*Assumptions!B12 -> -1214.5 | D20: =-D8*Assumptions!B12 -> -2578.065 | E20: =-E8*Assumptions!B12 -> -4600.723 | F20: =-F8*Assumptions!B12 -> -7437.7014 | G20: =-G8*Assumptions!B12 -> -11064.57 | H20: =-H8*Assumptions!B12 -> -15282.633 | I20: =-I8*Assumptions!B12 -> -20074.154 | J20: =-J8*Assumptions!B12 -> -25421.93 | K20: =-K8*Assumptions!B12 -> -31134.272 | L20: =-L8*Assumptions!B12 -> -37025.244 | M20: =-M8*Assumptions!B12 -> -42914.486 | N20: =SUM(B20:M20) -> -199098.28
A21: Tech + infra | B21: =-B8*Assumptions!B13 -> -750 | C21: =-C8*Assumptions!B13 -> -2602.5 | D21: =-D8*Assumptions!B13 -> -5524.425 | E21: =-E8*Assumptions!B13 -> -9858.6923 | F21: =-F8*Assumptions!B13 -> -15937.931 | G21: =-G8*Assumptions!B13 -> -23709.794 | H21: =-H8*Assumptions!B13 -> -32748.5 | I21: =-I8*Assumptions!B13 -> -43016.045 | J21: =-J8*Assumptions!B13 -> -54475.563 | K21: =-K8*Assumptions!B13 -> -66716.296 | L21: =-L8*Assumptions!B13 -> -79339.808 | M21: =-M8*Assumptions!B13 -> -91959.613 | N21: =SUM(B21:M21) -> -426639.17
A22: Support + overhead | B22: =-B8*Assumptions!B14 -> -750 | C22: =-C8*Assumptions!B14 -> -2602.5 | D22: =-D8*Assumptions!B14 -> -5524.425 | E22: =-E8*Assumptions!B14 -> -9858.6923 | F22: =-F8*Assumptions!B14 -> -15937.931 | G22: =-G8*Assumptions!B14 -> -23709.794 | H22: =-H8*Assumptions!B14 -> -32748.5 | I22: =-I8*Assumptions!B14 -> -43016.045 | J22: =-J8*Assumptions!B14 -> -54475.563 | K22: =-K8*Assumptions!B14 -> -66716.296 | L22: =-L8*Assumptions!B14 -> -79339.808 | M22: =-M8*Assumptions!B14 -> -91959.613 | N22: =SUM(B22:M22) -> -426639.17
A23: Add-on COGS | B23: =-B8*Assumptions!B34*(1-Assumptions!B35) -> -2400 | C23: =-C8*Assumptions!B34*(1-Assumptions!B35) -> -8328 | D23: =-D8*Assumptions!B34*(1-Assumptions!B35) -> -17678.16 | E23: =-E8*Assumptions!B34*(1-Assumptions!B35) -> -31547.815 | F23: =-F8*Assumptions!B34*(1-Assumptions!B35) -> -51001.381 | G23: =-G8*Assumptions!B34*(1-Assumptions!B35) -> -75871.339 | H23: =-H8*Assumptions!B34*(1-Assumptions!B35) -> -104795.2 | I23: =-I8*Assumptions!B34*(1-Assumptions!B35) -> -137651.34 | J23: =-J8*Assumptions!B34*(1-Assumptions!B35) -> -174321.8 | K23: =-K8*Assumptions!B34*(1-Assumptions!B35) -> -213492.15 | L23: =-L8*Assumptions!B34*(1-Assumptions!B35) -> -253887.38 | M23: =-M8*Assumptions!B34*(1-Assumptions!B35) -> -294270.76 | N23: =SUM(B23:M23) -> -1365245.3
A24: COGS (STAFF CAPACITY)
A25: Physicians needed (FTE) | B25: =MAX(1,CEILING(B7/Assumptions!B18,1)) -> 1 | C25: =MAX(1,CEILING(C7/Assumptions!B18,1)) -> 1 | D25: =MAX(1,CEILING(D7/Assumptions!B18,1)) -> 1 | E25: =MAX(1,CEILING(E7/Assumptions!B18,1)) -> 1 | F25: =MAX(1,CEILING(F7/Assumptions!B18,1)) -> 2 | G25: =MAX(1,CEILING(G7/Assumptions!B18,1)) -> 2 | H25: =MAX(1,CEILING(H7/Assumptions!B18,1)) -> 3 | I25: =MAX(1,CEILING(I7/Assumptions!B18,1)) -> 4 | J25: =MAX(1,CEILING(J7/Assumptions!B18,1)) -> 5 | K25: =MAX(1,CEILING(K7/Assumptions!B18,1)) -> 5 | L25: =MAX(1,CEILING(L7/Assumptions!B18,1)) -> 6 | M25: =MAX(1,CEILING(M7/Assumptions!B18,1)) -> 7 | N25: =SUM(B25:M25) -> 38
A26: Physician cost | B26: =-B25*Assumptions!B17 -> -180000 | C26: =-C25*Assumptions!B17 -> -180000 | D26: =-D25*Assumptions!B17 -> -180000 | E26: =-E25*Assumptions!B17 -> -180000 | F26: =-F25*Assumptions!B17 -> -360000 | G26: =-G25*Assumptions!B17 -> -360000 | H26: =-H25*Assumptions!B17 -> -540000 | I26: =-I25*Assumptions!B17 -> -720000 | J26: =-J25*Assumptions!B17 -> -900000 | K26: =-K25*Assumptions!B17 -> -900000 | L26: =-L25*Assumptions!B17 -> -1080000 | M26: =-M25*Assumptions!B17 -> -1260000 | N26: =SUM(B26:M26) -> -6840000
A27: Care leads needed (FTE) | B27: =MAX(1,CEILING(B7/Assumptions!B22,1)) -> 1 | C27: =MAX(1,CEILING(C7/Assumptions!B22,1)) -> 1 | D27: =MAX(1,CEILING(D7/Assumptions!B22,1)) -> 1 | E27: =MAX(1,CEILING(E7/Assumptions!B22,1)) -> 1 | F27: =MAX(1,CEILING(F7/Assumptions!B22,1)) -> 1 | G27: =MAX(1,CEILING(G7/Assumptions!B22,1)) -> 2 | H27: =MAX(1,CEILING(H7/Assumptions!B22,1)) -> 2 | I27: =MAX(1,CEILING(I7/Assumptions!B22,1)) -> 3 | J27: =MAX(1,CEILING(J7/Assumptions!B22,1)) -> 3 | K27: =MAX(1,CEILING(K7/Assumptions!B22,1)) -> 4 | L27: =MAX(1,CEILING(L7/Assumptions!B22,1)) -> 4 | M27: =MAX(1,CEILING(M7/Assumptions!B22,1)) -> 5 | N27: =SUM(B27:M27) -> 28
A28: Care lead cost | B28: =-B27*Assumptions!B21 -> -40000 | C28: =-C27*Assumptions!B21 -> -40000 | D28: =-D27*Assumptions!B21 -> -40000 | E28: =-E27*Assumptions!B21 -> -40000 | F28: =-F27*Assumptions!B21 -> -40000 | G28: =-G27*Assumptions!B21 -> -80000 | H28: =-H27*Assumptions!B21 -> -80000 | I28: =-I27*Assumptions!B21 -> -120000 | J28: =-J27*Assumptions!B21 -> -120000 | K28: =-K27*Assumptions!B21 -> -160000 | L28: =-L27*Assumptions!B21 -> -160000 | M28: =-M27*Assumptions!B21 -> -200000 | N28: =SUM(B28:M28) -> -1120000
A29: Total COGS | B29: =SUM(B18:B23)+B26+B28 -> -233850 | C29: =SUM(C18:C23)+C26+C28 -> -268059.5 | D29: =SUM(D18:D23)+D26+D28 -> -322017.72 | E29: =SUM(E18:E23)+E26+E28 -> -402057.18 | F29: =SUM(F18:F23)+F26+F28 -> -694320.47 | G29: =SUM(G18:G23)+G26+G28 -> -877840.85 | H29: =SUM(H18:H23)+H26+H28 -> -1224755.6 | I29: =SUM(I18:I23)+I26+I28 -> -1634363 | ... M29: =SUM(M18:M23)+M26+M28 -> -3158187.5 | N29: =SUM(B29:M29) -> -15838603
A30: Rx margin uplift | B30: =B8*Assumptions!B36 -> 2500 | C30: =C8*Assumptions!B36 -> 8675 | D30: =D8*Assumptions!B36 -> 18414.75 | E30: =E8*Assumptions!B36 -> 32862.308 | F30: =F8*Assumptions!B36 -> 53126.438 | G30: =G8*Assumptions!B36 -> 79032.645 | H30: =H8*Assumptions!B36 -> 109161.67 | I30: =I8*Assumptions!B36 -> 143386.82 | J30: =J8*Assumptions!B36 -> 181585.21 | K30: =K8*Assumptions!B36 -> 222387.65 | L30: =L8*Assumptions!B36 -> 264466.03 | M30: =M8*Assumptions!B36 -> 306532.04 | N30: =SUM(B30:M30) -> 1422130.6
A31: Gross profit | B31: =B15+B29+B30 -> -154246 | C31: =C15+C29+C30 -> 8166.38 | D31: =D15+D29+D30 -> 264337.39 | E31: =E15+E29+E30 -> 644331.27 | F31: =F15+F29+F30 -> 997310.33 | G31: =G15+G29+G30 -> 1638685 | H31: =H15+H29+H30 -> 2251126.5 | I31: =I15+I29+I30 -> 2931302.7 | ... M31: =M15+M29+M30 -> 6602283.2 | N31: =SUM(B31:M31) -> 29444309
A32: Gross margin % | B32: =IFERROR(B31/B13,0) -> -1.952481 | C32: =IFERROR(C31/C13,0) -> 0.029790173 | D32: =IFERROR(D31/D13,0) -> 0.45426124 | E32: =IFERROR(E31/E13,0) -> 0.62047469 | F32: =IFERROR(F31/F13,0) -> 0.59406304 | G32: =IFERROR(G31/G13,0) -> 0.65614811 | H32: =IFERROR(H31/H13,0) -> 0.65259337 | I32: =IFERROR(I31/I13,0) -> 0.64694053 | ... M32: =IFERROR(M31/M13,0) -> 0.68160252 | N32: =SUM(B32:M32) -> 4.4034072
A34: OPEX
A35: Marketing | B35: =-B5*Assumptions!B32 -> -120000 | C35: =-C5*Assumptions!B32 -> -180000 | D35: =-D5*Assumptions!B32 -> -300000 | E35: =-E5*Assumptions!B32 -> -420000 | F35: =-F5*Assumptions!B32 -> -600000 | G35: =-G5*Assumptions!B32 -> -720000 | H35: =-H5*Assumptions!B32 -> -840000 | I35: =-I5*Assumptions!B32 -> -960000 | J35: =-J5*Assumptions!B32 -> -1080000 | K35: =-K5*Assumptions!B32 -> -1140000 | L35: =-L5*Assumptions!B32 -> -1200000 | M35: =-M5*Assumptions!B32 -> -1200000 | N35: =SUM(B35:M35) -> -8760000
A36: G&A | B36: =-B13*Assumptions!B29 -> -11850 | C36: =-C13*Assumptions!B29 -> -41119.5 | D36: =-D13*Assumptions!B29 -> -87285.915 | E36: =-E13*Assumptions!B29 -> -155767.34 | F36: =-F13*Assumptions!B29 -> -251819.32 | G36: =-G13*Assumptions!B29 -> -374614.74 | H36: =-H13*Assumptions!B29 -> -517426.3 | I36: =-I13*Assumptions!B29 -> -679653.51 | J36: =-J13*Assumptions!B29 -> -860713.9 | K36: =-K13*Assumptions!B29 -> -1054117.5 | L36: =-L13*Assumptions!B29 -> -1253569 | M36: =-M13*Assumptions!B29 -> -1452961.9 | N36: =SUM(B36:M36) -> -6740898.8
A37: Total OpEx | B37: =B35+B36 -> -131850 | C37: =C35+C36 -> -221119.5 | D37: =D35+D36 -> -387285.91 | E37: =E35+E36 -> -575767.34 | F37: =F35+F36 -> -851819.32 | G37: =G35+G36 -> -1094614.7 | H37: =H35+H36 -> -1357426.3 | I37: =I35+I36 -> -1639653.5 | ... M37: =M35+M36 -> -2652961.9 | N37: =SUM(B37:M37) -> -15500899
A38: Operating profit | B38: =B31+B37 -> -286096 | C38: =C31+C37 -> -212953.12 | D38: =D31+D37 -> -122948.53 | E38: =E31+E37 -> 68563.929 | F38: =F31+F37 -> 145491.01 | G38: =G31+G37 -> 544070.28 | H38: =H31+H37 -> 893700.17 | I38: =I31+I37 -> 1291649.2 | ... M38: =M31+M37 -> 3949321.3 | N38: =SUM(B38:M38) -> 13943410
A39: Operating margin % | B39: =IFERROR(B38/B13,0) -> -3.6214684 | C39: =IFERROR(C38/C13,0) -> -0.7768326 | D39: =IFERROR(D38/D13,0) -> -0.21128585 | E39: =IFERROR(E38/E13,0) -> 0.066025327 | F39: =IFERROR(F38/F13,0) -> 0.08666393 | G39: =IFERROR(G38/G13,0) -> 0.21785193 | H39: =IFERROR(H38/H13,0) -> 0.25908043 | I39: =IFERROR(I38/I13,0) -> 0.28506787 | ... M39: =IFERROR(M38/M13,0) -> 0.40771764 | N39: =SUM(B39:M39) -> -2.2111921
